export const OP_NOP = 0x00
export const OP_ACONST_NULL = 0x01
export const OP_ICONST_M1 = 0x02
export const OP_ICONST_0 = 0x03
export const OP_ICONST_1 = 0x04
export const OP_ICONST_2 = 0x05
export const OP_ICONST_3 = 0x06
export const OP_ICONST_4 = 0x07
export const OP_ICONST_5 = 0x08
export const OP_LCONST_0 = 0x09
export const OP_LCONST_1 = 0x0a
export const OP_FCONST_0 = 0x0b
export const OP_FCONST_1 = 0x0c
export const OP_FCONST_2 = 0x0d
export const OP_DCONST_0 = 0x0e
export const OP_DCONST_1 = 0x0f
export const OP_BIPUSH = 0x10
export const OP_SIPUSH = 0x11
export const OP_LDC = 0x12
export const OP_LDC_W = 0x13
export const OP_LDC2_W = 0x14
export const OP_ILOAD = 0x15
export const OP_LLOAD = 0x16
export const OP_FLOAD = 0x17
export const OP_DLOAD = 0x18
export const OP_ALOAD = 0x19
export const OP_ILOAD_0 = 0x1a
export const OP_ILOAD_1 = 0x1b
export const OP_ILOAD_2 = 0x1c
export const OP_ILOAD_3 = 0x1d
export const OP_LLOAD_0 = 0x1e
export const OP_LLOAD_1 = 0x1f
export const OP_LLOAD_2 = 0x20
export const OP_LLOAD_3 = 0x21
export const OP_FLOAD_0 = 0x22
export const OP_FLOAD_1 = 0x23
export const OP_FLOAD_2 = 0x24
export const OP_FLOAD_3 = 0x25
export const OP_DLOAD_0 = 0x26
export const OP_DLOAD_1 = 0x27
export const OP_DLOAD_2 = 0x28
export const OP_DLOAD_3 = 0x29
export const OP_ALOAD_0 = 0x2a
export const OP_ALOAD_1 = 0x2b
export const OP_ALOAD_2 = 0x2c
export const OP_ALOAD_3 = 0x2d
export const OP_IALOAD = 0x2e
export const OP_LALOAD = 0x2f
export const OP_FALOAD = 0x30
export const OP_DALOAD = 0x31
export const OP_AALOAD = 0x32
export const OP_BALOAD = 0x33
export const OP_CALOAD = 0x34
export const OP_SALOAD = 0x35
export const OP_ISTORE = 0x36
export const OP_LSTORE = 0x37
export const OP_FSTORE = 0x38
export const OP_DSTORE = 0x39
export const OP_ASTORE = 0x3a
export const OP_ISTORE_0 = 0x3b
export const OP_ISTORE_1 = 0x3c
export const OP_ISTORE_2 = 0x3d
export const OP_ISTORE_3 = 0x3e
export const OP_LSTORE_0 = 0x3f
export const OP_LSTORE_1 = 0x40
export const OP_LSTORE_2 = 0x41
export const OP_LSTORE_3 = 0x42
export const OP_FSTORE_0 = 0x43
export const OP_FSTORE_1 = 0x44
export const OP_FSTORE_2 = 0x45
export const OP_FSTORE_3 = 0x46
export const OP_DSTORE_0 = 0x47
export const OP_DSTORE_1 = 0x48
export const OP_DSTORE_2 = 0x49
export const OP_DSTORE_3 = 0x4a
export const OP_ASTORE_0 = 0x4b
export const OP_ASTORE_1 = 0x4c
export const OP_ASTORE_2 = 0x4d
export const OP_ASTORE_3 = 0x4e
export const OP_IASTORE = 0x4f
export const OP_LASTORE = 0x50
export const OP_FASTORE = 0x51
export const OP_DASTORE = 0x52
export const OP_AASTORE = 0x53
export const OP_BASTORE = 0x54
export const OP_CASTORE = 0x55
export const OP_SASTORE = 0x56
export const OP_POP = 0x57
export const OP_POP2 = 0x58
export const OP_DUP = 0x59
export const OP_DUP_X1 = 0x5a
export const OP_DUP_X2 = 0x5b
export const OP_DUP2 = 0x5c
export const OP_DUP2_X1 = 0x5d
export const OP_DUP2_X2 = 0x5e
export const OP_SWAP = 0x5f
export const OP_IADD = 0x60
export const OP_LADD = 0x61
export const OP_FADD = 0x62
export const OP_DADD = 0x63
export const OP_ISUB = 0x64
export const OP_LSUB = 0x65
export const OP_FSUB = 0x66
export const OP_DSUB = 0x67
export const OP_IMUL = 0x68
export const OP_LMUL = 0x69
export const OP_FMUL = 0x6a
export const OP_DMUL = 0x6b
export const OP_IDIV = 0x6c
export const OP_LDIV = 0x6d
export const OP_FDIV = 0x6e
export const OP_DDIV = 0x6f
export const OP_IREM = 0x70
export const OP_LREM = 0x71
export const OP_FREM = 0x72
export const OP_DREM = 0x73
export const OP_INEG = 0x74
export const OP_LNEG = 0x75
export const OP_FNEG = 0x76
export const OP_DNEG = 0x77
export const OP_ISHL = 0x78
export const OP_LSHL = 0x79
export const OP_ISHR = 0x7a
export const OP_LSHR = 0x7b
export const OP_IUSHR = 0x7c
export const OP_LUSHR = 0x7d
export const OP_IAND = 0x7e
export const OP_LAND = 0x7f
export const OP_IOR = 0x80
export const OP_LOR = 0x81
export const OP_IXOR = 0x82
export const OP_LXOR = 0x83
export const OP_IINC = 0x84
export const OP_I2L = 0x85
export const OP_I2F = 0x86
export const OP_I2D = 0x87
export const OP_L2I = 0x88
export const OP_L2F = 0x89
export const OP_L2D = 0x8a
export const OP_F2I = 0x8b
export const OP_F2L = 0x8c
export const OP_F2D = 0x8d
export const OP_D2I = 0x8e
export const OP_D2L = 0x8f
export const OP_D2F = 0x90
export const OP_I2B = 0x91
export const OP_I2C = 0x92
export const OP_I2S = 0x93
export const OP_LCMP = 0x94
export const OP_FCMPL = 0x95
export const OP_FCMPG = 0x96
export const OP_DCMPL = 0x97
export const OP_DCMPG = 0x98
export const OP_IFEQ = 0x99
export const OP_IFNE = 0x9a
export const OP_IFLT = 0x9b
export const OP_IFGE = 0x9c
export const OP_IFGT = 0x9d
export const OP_IFLE = 0x9e
export const OP_IF_ICMPEQ = 0x9f
export const OP_IF_ICMPNE = 0xa0
export const OP_IF_ICMPLT = 0xa1
export const OP_IF_ICMPGE = 0xa2
export const OP_IF_ICMPGT = 0xa3
export const OP_IF_ICMPLE = 0xa4
export const OP_IF_ACMPEQ = 0xa5
export const OP_IF_ACMPNE = 0xa6
export const OP_GOTO = 0xa7
export const OP_JSR = 0xa8
export const OP_RET = 0xa9
export const OP_TABLESWITCH = 0xaa
export const OP_LOOKUPSWITCH = 0xab
export const OP_IRETURN = 0xac
export const OP_LRETURN = 0xad
export const OP_FRETURN = 0xae
export const OP_DRETURN = 0xaf
export const OP_ARETURN = 0xb0
export const OP_RETURN = 0xb1
export const OP_GETSTATIC = 0xb2
export const OP_PUTSTATIC = 0xb3
export const OP_GETFIELD = 0xb4
export const OP_PUTFIELD = 0xb5
export const OP_INVOKEVIRTUAL = 0xb6
export const OP_INVOKESPECIAL = 0xb7
export const OP_INVOKESTATIC = 0xb8
export const OP_INVOKEINTERFACE = 0xb9
export const OP_INVOKEDYNAMIC = 0xba
export const OP_NEW = 0xbb
export const OP_NEWARRAY = 0xbc
export const OP_ANEWARRAY = 0xbd
export const OP_ARRAYLENGTH = 0xbe
export const OP_ATHROW = 0xbf
export const OP_CHECKCAST = 0xc0
export const OP_INSTANCEOF = 0xc1
export const OP_MONITORENTER = 0xc2
export const OP_MONITOREXIT = 0xc3
export const OP_WIDE = 0xc4
export const OP_MULTIANEWARRAY = 0xc5
export const OP_IFNULL = 0xc6
export const OP_IFNONNULL = 0xc7
export const OP_GOTO_W = 0xc8
export const OP_JSR_W = 0xc9
export const OP_BREAKPOINT = 0xca

export const OP_IMPDEP1 = 0xfe
export const OP_IMPDEP2 = 0xff

export const OP_NAMES = [
  'nop',
  'aconst_null',
  'iconst_m1', 'iconst_0', 'iconst_1', 'iconst_2', 'iconst_3', 'iconst_4', 'iconst_5',
  'lconst_0', 'lconst_1',
  'fconst_0', 'fconst_1', 'fconst_2',
  'dconst_0', 'dconst_1',
  'bipush', 'sipush',
  'ldc', 'ldc_w', 'ldc2_w',
  'iload', 'lload', 'fload', 'dload', 'aload',
  'iload_0', 'iload_1', 'iload_2', 'iload_3',
  'lload_0', 'lload_1', 'lload_2', 'lload_3',
  'fload_0', 'fload_1', 'fload_2', 'fload_3',
  'dload_0', 'dload_1', 'dload_2', 'dload_3',
  'aload_0', 'aload_1', 'aload_2', 'aload_3',
  'iaload', 'laload', 'faload', 'daload', 'aaload', 'baload', 'caload', 'saload',
  'istore', 'lstore', 'fstore', 'dstore', 'astore',
  'istore_0', 'istore_1', 'istore_2', 'istore_3',
  'lstore_0', 'lstore_1', 'lstore_2', 'lstore_3',
  'fstore_0', 'fstore_1', 'fstore_2', 'fstore_3',
  'dstore_0', 'dstore_1', 'dstore_2', 'dstore_3',
  'astore_0', 'astore_1', 'astore_2', 'astore_3',
  'iastore', 'lastore', 'fastore', 'dastore', 'aastore', 'bastore', 'castore', 'sastore',
  'pop', 'pop2',
  'dup', 'dup_x1', 'dup_x2', 'dup2', 'dup2_x1', 'dup2_x2',
  'swap',
  'iadd', 'ladd', 'fadd', 'dadd',
  'isub', 'lsub', 'fsub', 'dsub',
  'imul', 'lmul', 'fmul', 'dmul',
  'idiv', 'ldiv', 'fdiv', 'ddiv',
  'irem', 'lrem', 'frem', 'drem',
  'ineg', 'lneg', 'fneg', 'dneg',
  'ishl', 'lshl',
  'ishr', 'lshr',
  'iushr', 'lushr',
  'iand', 'land',
  'ior', 'lor',
  'ixor', 'lxor',
  'iinc',
  'i2l', 'i2f', 'i2d',
  'l2i', 'l2f', 'l2d',
  'f2i', 'f2l', 'f2d',
  'd2i', 'd2l', 'd2f',
  'i2b', 'i2c', 'i2s',
  'lcmp',
  'fcmpl', 'fcmpg',
  'dcmpl', 'dcmpg',
  'ifeq', 'ifne', 'iflt', 'ifge', 'ifgt', 'ifle',
  'if_icmpeq', 'if_icmpne', 'if_icmplt', 'if_icmpge', 'if_icmpgt', 'if_icmple',
  'if_acmpeq', 'if_acmpne',
  'goto', 'jsr', 'ret',
  'tableswitch', 'lookupswitch',
  'ireturn', 'lreturn', 'freturn', 'dreturn', 'areturn', 'return',
  'getstatic', 'putstatic',
  'getfield', 'putfield',
  'invokevirtual', 'invokespecial', 'invokestatic', 'invokeinterface', 'invokedynamic',
  'new', 'newarray', 'anewarray',
  'arraylength',
  'athrow',
  'checkcast', 'instanceof',
  'monitorenter', 'monitorexit',
  'wide',
  'multianewarray',
  'ifnull', 'ifnonnull',
  'goto_w', 'jsr_w',
  'breakpoint'
]

OP_NAMES[OP_IMPDEP1] = 'impdep1'
OP_NAMES[OP_IMPDEP2] = 'impdep2'

/* eslint-disable camelcase */
export const CONSTANT_Utf8 = 1
export const CONSTANT_Integer = 3
export const CONSTANT_Float = 4
export const CONSTANT_Long = 5
export const CONSTANT_Double = 6
export const CONSTANT_Class = 7
export const CONSTANT_String = 8
export const CONSTANT_Fieldref = 9
export const CONSTANT_Methodref = 10
export const CONSTANT_InterfaceMethodref = 11
export const CONSTANT_NameAndType = 12
export const CONSTANT_MethodHandle = 15
export const CONSTANT_MethodType = 16
export const CONSTANT_Dynamic = 17
export const CONSTANT_InvokeDynamic = 18
export const CONSTANT_Module = 19
export const CONSTANT_Package = 20
/* esline-enable camelcase */
